tests/__init__.py
tests/test_cli.py
tests/test_github_util.py
tests/test_json.py
tjauto/__init__.py
tjauto/cli_util.py
tjauto/collection_util.py
tjauto/file_util.py
tjauto/git_util.py
tjauto/github_util.py
tjauto/json_util.py
tjauto/yaml_util.py
tjauto-0.0.1.dist-info/LICENSE
tjauto-0.0.1.dist-info/METADATA
tjauto-0.0.1.dist-info/WHEEL
tjauto-0.0.1.dist-info/top_level.txt
tjauto-0.0.1.dist-info/RECORD
