Metadata-Version: 2.1
Name: tjauto
Version: 0.0.1
Summary: A automation util set
Home-page: https://github.com/jtong/tjauto
Author: T,J
Author-email: tj19832@gmail.com
License: UNKNOWN
Platform: UNKNOWN
Classifier: Programming Language :: Python :: 3
Classifier: License :: OSI Approved :: MIT License
Classifier: Operating System :: OS Independent
Requires-Python: >=3.9
